{"cdn.taboola.com": "52577584", "huobi.com": "52577585", "mature.x-cdn.top": "52577587", "ru.sex-studentki.dev": "52577588", "cstatic.weborama.fr": "52577590", "gw.aeroflot.ru": "52577591", "translate.googleapis.com": "52577592", "piratgo.mobi": "52577594", "cdn.optimizely.com": "52577595", "api-support.neuralgeneration.com": "52577596", "livescore.in": "52577597", "pixel.tapad.com": "52577598", "com-x.life": "52577599", "ru.dotabuff.com": "52577600", "10075061.fls.doubleclick.net": "52577601", "r.casalemedia.com": "52577603", "firebaseinstallations.googleapis.com": "52577604", "959dfe38280d0bc430735b4853c2193e.safeframe.googlesyndication.com": "52577605", "gu-st.ru": "52577606", "scontent.whatsapp.net": "52577862", "tmssl.akamaized.net": "52577863", "widget-pixels.outbrain.com": "52577864", "ssl.gstatic.com": "52577865", "scripts.ssm.codes": "52577866", "dynamic-media-cdn.tripadvisor.com": "52577867", "pbs.twimg.com": "52577868", "static.vidazoo.com": "52577869", "cdn.sstatic.net": "52577872", "ir.ebaystatic.com": "52577873", "d.turn.com": "52577874", "lexicon.33across.com": "52577875", "cdn.plyr.io": "52577876", "cdn-sp.kertn.net": "52577877", "support.microsoft.com": "52577878", "audiencedata.im-apps.net": "52577879", "meet.bluesystem.me": "52577880", "rotator.adsmediator.com": "52577881", "assets.genius.com": "52577882", "topwar.ru": "52577883", "mangahub.ru": "52577884", "maxcdn.bootstrapcdn.com": "52577885", "terraria-game.fandom.com": "52578249", "ga-tracker-dot-detmir-bonus.appspot.com": "52578251", "i-invdn-com.investing.com": "52578253", "sync.teads.tv": "52578254", "c.statcounter.com": "52578255", "cdn.jsdelivr.net": "52578257", "happymodapk.ru": "52578259", "m.bdsmpeople.co": "52578260", "s.go-mpulse.net": "52578262", "kniga-online.com": "52578265", "hltv.org": "52578266", "hsto.org": "52578268", "content.hybrid.ai": "52578270", "rus.bongacams21.com": "52578271", "c1.adform.net": "52578273", "aeroflot.ru": "52578275", "cm.g.doubleclick.net": "52578276", "cm.adform.net": "52578277", "iqtestcc.b-cdn.net": "52578279", "artstation.com": "52578280", "ecomir.uchi.ru": "52578668", "appleid.cdn-apple.com": "52578669", "ads.assemblyexchange.com": "52578670", "performance.radar.cloudflare.com": "52578674", "m.yaeby.art": "52578675", "mcgrp.ru": "52578676", "test.octolinkcom.me": "52578677", "ranobes.com": "52578678", "ad.turn.com": "52578679", "tripadvisor.ru": "52578680", "ussurmedia.ru": "52578681", "vseinstrumenti.ru": "52578683", "forums.e-hentai.org": "52578684", "bin.bnbstatic.com": "52578685", "hbg-prod-fed-public.hbfile.net": "52578686", "i.clean.gg": "52578687", "checkporno.com": "52578688", "static.parastorage.com": "52578689", "cdek.shopping": "52578690", "api.mixpanel.com": "52578691", "redirector.gvt1.com": "52578693", "s1.rusvideos.mobi": "52578694", "static.cdninstagram.com": "52578695", "googleadservices.com": "52579023", "nnmclub.to": "52579024", "da.codenet.one": "52579026", "g.c.appier.net": "52579027", "api.github.com": "52579028", "wp.24smi.org": "52579029", "static.adroute.focas.jp": "52579030", "c.s-microsoft.com": "52579031", "ru.bongacams26.com": "52579032", "widgets-04.livetex.me": "52579034", "us-u.openx.net": "52579035", "meshok.net": "52579130", "report.daumoon.com": "52579131", "fragrantica.ru": "52579132", "api.btloader.com": "52579133", "ru.freepik.com": "52579134", "avatars.steamstatic.com": "52579136", "cdn.static.zdbb.net": "52579137", "gql.twitch.tv": "52579139", "files.vgtimes.ru": "52579140", "vgtimes.ru": "52579141", "cdn.cian.site": "52579142", "super.rusvideos.online": "52579143", "ds.frontend.weborama.fr": "52579144", "binance.com": "52579260", "i1.ytimg.com": "52579262", "fandom.com": "52579263", "ss.sport-express.ru": "52579264", "a.pub.network": "52579265", "streaming.forexpros.com": "52579266", "city.bluesystem.me": "52579267", "matching.ivitrack.com": "52579268", "google-analytics.bi.owox.com": "52579269", "doramafox.ru": "52579270", "youtube-nocookie.com": "52579271", "notifications.neuralgeneration.com": "52579272", "api.coinmarketcap.com": "52579273", "sbermarket.ru": "52579274", "storage.octoclick.com": "52579276", "porno365.nz": "52579277", "googleads.g.doubleclick.net": "52579278", "static.whatsapp.net": "52579279", "s73937.cdn.ngenix.net": "52579280", "buttons-config.sharethis.com": "52579281", "yclients.com": "52579282", "40.img.avito.st": "52579283", "statcounter.com": "52579284", "c.go-mpulse.net": "52579285", "static.doubleclick.net": "52579676", "d.livescore.in": "52579677", "m.vten.ru": "52579678", "tracker.luckypush.pro": "52579679", "data.ad-score.com": "52579680", "kstatic.googleusercontent.com": "52579682", "myactivity.google.com": "52579683", "primamedia.ru": "52579684", "cse.google.com": "52579686", "pre.glotgrx.com": "52579687", "zn394yygoj0zd35dd-cbs.siteintercept.qualtrics.com": "52579688", "10756659.fls.doubleclick.net": "52579689", "ex.24smi.info": "52579690", "11536333.fls.doubleclick.net": "52579691", "7c16c0869b022628c76cfe9e121597d2.safeframe.googlesyndication.com": "52579692", "prod-video-cms-rt-microsoft-com.akamaized.net": "52579693", "widget.retell.cc": "52579695", "ampcid.google.com": "52579696", "dcdn2.heroeswm.ru": "52579698", "wf.frontend.weborama.fr": "52579699", "ru.fap-guru.art": "52579700", "somon.tj": "52579701", "api.rlcdn.com": "52579702", "heroeswm.ru": "52579703", "img.freepik.com": "52579808", "googleads4.g.doubleclick.net": "52579810", "cdn.somon.tj": "52579811", "img6.eadaily.com": "52579812", "cdn2.randewoo.ru": "52579813", "widgets.outbrain.com": "52579814", "cdn.onesignal.com": "52579815", "genshindrop.push4site.com": "52579816", "ficbook.net": "52579817", "s91588.cdn.ngenix.net": "52579818", "nerabota.center": "52579819", "cm.rtbsystem.com": "52579820", "socpublic.com": "52579821", "maxreacts.com": "52579945", "russianfood.com": "52579946", "translate.google.ru": "52579947", "platform.foremedia.net": "52579948", "androeed.store": "52579950", "promokodi.net": "52579951", "c.xn----itbkgb9adccau2a.click": "52579952", "a.clickcertain.com": "52579953", "encrypted-tbn3.gstatic.com": "52579954", "hentailib.me": "52579955", "stat4.russianfood.com": "52579956", "12638050.fls.doubleclick.net": "52579957", "a.thumbs.redditmedia.com": "52579958", "f.sravni.ru": "52579959", "open.woodpeckerlog.com": "52579960", "odkl.xospital.mobi": "52579961", "rtstat.api.rt.com": "52579962", "api.sravni.ru": "52579965", "spb.cian.ru": "52579966", "gen.jut.su": "52579967", "list.am": "52579968", "promo.livelib.ru": "52579969", "img.a.transfermarkt.technology": "52579970", "tegos.club": "52579971", "chimpstatic.com": "52580154", "sf16-website-login.neutral.ttwstatic.com": "52580155", "ggstandoff.app": "52580156", "o1282968.ingest.sentry.io": "52580157", "instagram.com": "52580158", "serieslife.online": "52580159", "intimshop.ru": "52580161", "static.clmbtech.com": "52580162", "browser.sentry-cdn.com": "52580163", "s.livelib.ru": "52580164", "static.aviasales.ru": "52580165", "staticdelivery.nexusmods.com": "52580166", "htlb.casalemedia.com": "52580167", "piratgo.ru": "52580168", "abs-0.twimg.com": "52580169", "p16-sign-sg.tiktokcdn.com": "52580170", "api.yclients.com": "52580171", "v1.popcornnews.ru": "52580173", "ads.playground.xyz": "52580174", "z.moatads.com": "52580175", "img1.vten.ru": "52580177", "enthusiastgaming-com.videoplayerhub.com": "52580178", "iv.kommersant.ru": "52580179", "starpets.gg": "52580181", "sentry.io": "52580400", "cdn-fluct.sh.adingo.jp": "52580401", "img5.24fastload.com": "52580402", "kinozal.tv": "52580403", "admin.neuralgeneration.com": "52580404", "c.amazon-adsystem.com": "52580405", "idsync.rlcdn.com": "52580406", "static.1000.menu": "52580407", "p1.zemanta.com": "52580408", "rule34.xxx": "52580411", "googletagmanager.com": "52580412", "astv.ru": "52580413", "wrappers.geoedge.be": "52580414", "g5.sunlight.net": "52580415", "googletagservices.com": "52580416", "myaccount.google.com": "52580417", "forum.baginya.org": "52580418", "steamcommunity.com": "52580419", "static.life.ru": "52580420", "akket.com": "52580421", "img.detmir.st": "52580422", "a.nvuti.care": "52580423", "yaoilib.me": "52580425", "support.google.com": "52580426", "img4.eadaily.com": "52580681", "cdn4.tu-tu.ru": "52580682", "beacon.wikia-services.com": "52580683", "secure-assets.rubiconproject.com": "52580684", "doubleclick.net": "52580685", "accounts.google.com": "52580687", "russian.rt.com": "52580688", "faberlic.com": "52580689", "jsn.24smi.net": "52580690", "img.bigbossss.com": "52580692", "nude-moon.org": "52580694", "policy.app.cookieinformation.com": "52580695", "whatismyip.li": "52580696", "unpkg.com": "52580697", "mn230126pb.com": "52580698", "artfut.com": "52580699", "rbmjs.com.ru": "52580700", "cdn.bulldrop.net": "52580701", "cdn77-pic.xvideos-cdn.com": "52580702", "data.nalog.ru": "52580703", "coinzillatag.com": "52580704", "bulldrop.net": "52580705", "zdstatic.speedtest.net": "52580706", "onesignal.com": "52580708", "mintmanga.live": "52580939", "file.hbfile.net": "52580940", "nnmstatic.win": "52580941", "sdk.privacy-center.org": "52580942", "blueimp.github.io": "52580943", "xxx.yaeby.info": "52580944", "data.24smi.net": "52580945", "fkwallet.ru": "52580946", "commonapi.fastviewdata.com": "52580947", "hbabit.com": "52580948", "bns.bluesystem.world": "52580949", "widget-api.uxfeedback.ru": "52580950", "ruso-oge.sdamgia.ru": "52580952", "m.loloo.ru": "52580953", "images.faberlic.com": "52580954", "emoji.redditmedia.com": "52580955", "posylka.net": "52580956", "mcs-va.tiktok.com": "52580957", "dmp.im-apps.net": "52580958", "koocyxvedfjjtpabewsdjbqpjoe1d1680945047.nuid.imrworldwide.com": "52580959", "services.fandom.com": "52580960", "static.adsafeprotected.com": "52580961", "static.bumlam.com": "52580962", "cdn.ziffstatic.com": "52580963", "static.cloudflareinsights.com": "52581169", "ads.elo.io": "52581170", "m.apkpure.com": "52581174", "10501859.fls.doubleclick.net": "52581175", "grouple.co": "52581177", "cdn2.ozone.ru": "52581178", "source.klops.ru": "52581179", "o346603.ingest.sentry.io": "52581180", "googleoptimize.com": "52581181", "cdn77-pic.xnxx-cdn.com": "52581182", "ams2-cdn.2gis.com": "52581184", "12731710.fls.doubleclick.net": "52581185", "privacyportal.onetrust.com": "52581186", "cdn.reverso.net": "52581187", "life.ru": "52581188", "cdn.intergient.com": "52581189", "v1.addthisedge.com": "52581190", "cm.author.today": "52581192", "byrut.org": "52581193", "ssl.google-analytics.com": "52581194", "aw.dw.impact-ad.jp": "52581195", "csync.loopme.me": "52581196", "drive.google.com": "52581197", "static-cdn77.xnxx-cdn.com": "52581198", "vsegda.love": "52581420", "idsync.frontend.weborama.fr": "52581421", "js-agent.newrelic.com": "52581423", "cm.everesttech.net": "52581424", "5play.ru": "52581425", "ad-delivery.net": "52581426", "ranobelib.me": "52581427", "prebid.mgid.com": "52581429", "ipapi.co": "52581430", "steamuserimages-a.akamaihd.net": "52581431", "preview.redd.it": "52581433", "lh3.googleusercontent.com": "52581434", "wap.teeda.ru": "52581435", "mp3uk.net": "52581437", "api-js.datadome.co": "52581438", "livechat.infobip.com": "52581439", "dclk-match.dotomi.com": "52581440", "static2.mangapoisk.com": "52581441", "wl-static.cf.tsp.li": "52581442", "newassets.hcaptcha.com": "52581443", "videouroki.net": "52581445", "cdn.hadronid.net": "52581447", "c.porno-me.club": "52581451", "pepper.ru": "52581453", "s.ytimg.com": "52581454", "img.pravda.ru": "52581672", "umschool.net": "52581673", "docs.ozon.ru": "52581676", "s3t3d2y8.afcdn.net": "52581678", "hermitage.aviasales.ru": "52581679", "tmsi.akamaized.net": "52581680", "items.neuralgeneration.com": "52581681", "fastly-insights.com": "52581682", "rr1---sn-f5f7lnld.googlevideo.com": "52581683", "mssdk-va.tiktok.com": "52581684", "rendez-vous.ru": "52581686", "static.ads-twitter.com": "52581687", "lf16-tiktok-web.ttwstatic.com": "52581689", "gstatic.com": "52581690", "amazon.com": "52581691", "freepik.cdnpk.net": "52581692", "2ch.hk": "52581694", "nyx-nyx-nyx.dotabuff.com": "52581695", "v16-webapp-prime.tiktok.com": "52581696", "news.ru": "52581697", "rt.udmserve.net": "52581698", "ege.sdamgia.ru": "52581700", "d7-invdn-com.investing.com": "52581701", "goroda.bluesystem.me": "52581702", "tile0.maps.2gis.com": "52581870", "soc-ege.sdamgia.ru": "52581872", "api.corr.life": "52581873", "images-wixmp-ed30a86b8c4ca887773594c2.wixmp.com": "52581875", "avatars.cloudflare.steamstatic.com": "52581876", "stackpath.bootstrapcdn.com": "52581877", "gurgle.speedtest.net": "52581878", "letu.ru": "52581879", "cdn.planeta-online.tv": "52581880", "furaffinity.net": "52581881", "olympiads.uchi.ru": "52581882", "xgroovy.com": "52581884", "wa.onelink.me": "52581885", "stackoverflow.com": "52581887", "9382251.fls.doubleclick.net": "52581888", "cdn.zvuk.com": "52581890", "rus.rusuchka.com": "52581891", "vipgdz.com": "52581893", "kinozal4me.live": "52581894", "last.fm": "52581895", "ct.pinterest.com": "52581897", "secure.insightexpressai.com": "52581898", "tpc.googlesyndication.com": "52581899", "translate.google.com": "52581900", "svyaznoy.ru": "52582188", "gql.reddit.com": "52582189", "adservice.google.com": "52582190", "www3.doubleclick.net": "52582191", "sessions.bugsnag.com": "52582192", "img3.eadaily.com": "52582193", "v2.vost.pw": "52582194", "img8.eadaily.com": "52582195", "ru.sexkomix2.com": "52582196", "static.chartbeat.com": "52582197", "static1.freebitco.in": "52582199", "static2.static1-sima-land.com": "52582200", "klops.ru": "52582201", "static.mangahub.ru": "52582202", "seller.ozon.ru": "52582203", "cdn1.tu-tu.ru": "52582204", "api.exponea.com": "52582205", "cdn-ukwest.onetrust.com": "52582206", "kerve.last.fm": "52582207", "oge.sdamgia.ru": "52582210", "alb.reddit.com": "52582211", "market.csgo.com": "52582212", "images0.androeed.ru": "52582213", "s2.getsitecontrol.com": "52582214", "academy-public.coinmarketcap.com": "52582525", "fonts.gstatic.com": "52582527", "id.hadron.ad.gt": "52582528", "everestjs.net": "52582530", "holywarsoo.net": "52582531", "s.glaz.tv": "52582533", "photo.hotellook.com": "52582534", "vplayer.enthusiastgaming.com": "52582535", "at.cbsi.com": "52582536", "img.nude-moon.org": "52582537", "casale-match.dotomi.com": "52582540", "engine.geniusaudience.com": "52582541", "api-public.addthis.com": "52582542", "securepubads.g.doubleclick.net": "52582543", "ads.avads.net": "52582544", "facebook.com": "52582545", "maps.googleapis.com": "52582546", "d1-invdn-com.investing.com": "52582548", "stream.coinmarketcap.com": "52582549", "captchas.freebitco.in": "52582551", "ssum.casalemedia.com": "52582552", "delivery.adrecover.com": "52582553", "ajax.googleapis.com": "52582554", "sdki.truepush.com": "52582556", "euroki.org": "52582890", "s3.coinmarketcap.com": "52582892", "s1.livelib.ru": "52582893", "20.img.avito.st": "52582895", "rrstatic.retailrocket.net": "52582896", "m.twitch.tv": "52582897", "gdz.ru": "52582898", "b.thumbs.redditmedia.com": "52582899", "nvuti.care": "52582900", "s.company-target.com": "52582901", "odkltown.fruitshake.mobi": "52582902", "ad.yieldlab.net": "52582904", "studio.youtube.com": "52582906", "doramy.club": "52582907", "smart-lab.ru": "52582909", "i.ytimg.com": "52582910", "eadaily.com": "52582911", "js.ad-score.com": "52582912", "adbtc.top": "52582913", "cdn3.static1-sima-land.com": "52582915", "static.rendez-vous.ru": "52582916", "web.whatsapp.com": "52582917", "eus.rubiconproject.com": "52582918", "o1125947.ingest.sentry.io": "52582919", "ads.travelaudience.com": "52583193", "jadekoi.ru": "52583194", "img.youtube.com": "52583198", "blusiki.bluesystem.world": "52583199", "speedtest.net": "52583200", "reshak.ru": "52583201", "static.tacdn.com": "52583202", "mp3uks.ru": "52583203", "4pda.to": "52583204", "dsum-sec.casalemedia.com": "52583205", "translate-pa.googleapis.com": "52583206", "i.ebayimg.com": "52583208", "docs.google.com": "52583209", "img2.eadaily.com": "52583210", "funpay.com": "52583211", "script.crazyegg.com": "52583212", "tiktok.com": "52583213", "t2.genius.com": "52583214", "xnxx3.com": "52583216", "mangalib.org": "52583217", "cache.betweendigital.com": "52583218", "google.ru": "52583219", "sales.neuralgeneration.com": "52583220", "js.vivoo.ru": "52583221", "csgopositive.me": "52583426", "tl.rulate.ru": "52583427", "a.tribalfusion.com": "52583428", "playerok.com": "52583429", "pagead2.googlesyndication.com": "52583430", "eccoru.push4site.com": "52583431", "edge.fullstory.com": "52583432", "lordserial.run": "52583433", "v1.yaoilib.me": "52583434", "push.coinmarketcap.com": "52583435", "doramatv.live": "52583437", "sensors.saasexch.com": "52583438", "tms-st.cdn.ngenix.net": "52583439", "rus.bongacams.com": "52583440", "rf.bongacams.com": "52583441", "rus.bonga-cams.com": "52583442", "lib.social": "52583443", "dcdn1.heroeswm.ru": "52583444", "fastlane.rubiconproject.com": "52583445", "google-analytics.com": "52583446", "load77.exelator.com": "52583447", "dmp.v.fwmrm.net": "52583448", "a.realsrv.com": "52583449", "dropi-ru.disqus.com": "52583450", "fundingchoicesmessages.google.com": "52583663", "galamart.ru": "52583664", "top-androidd.ru": "52583665", "lf16-tiktok-common.ibytedtos.com": "52583666", "starling-oversea.byteoversea.com": "52583667", "themes.googleusercontent.com": "52583668", "trades.neuralgeneration.com": "52583669", "ru9.trahkino.club": "52583670", "ilovepdf.com": "52583671", "static.pepper.ru": "52583672", "avatars.githubusercontent.com": "52583673", "img.tsargrad.tv": "52583674", "v.redd.it": "52583675", "cdn.adsafeprotected.com": "52583676", "staticstats.nexusmods.com": "52583678", "chatubate.me": "52583679", "lordserial.la": "52583680", "rus-oge.sdamgia.ru": "52583681", "vezonchik.mobi": "52583682", "images.prismic.io": "52583683", "img1.russianfood.com": "52583684", "rutracker.org": "52583685", "eldenring.fandom.com": "52583686", "youtube.com": "52583914", "ntv-static.cdnvideo.ru": "52583915", "pixel.yabidos.com": "52583916", "external-preview.redd.it": "52583918", "static.rutracker.cc": "52583919", "coinmarketcap.com": "52583920", "p16-sign-va.tiktokcdn.com": "52583921", "cdnvideo-static-ssl.domashniy.ru": "52583922", "vc.ru": "52583923", "township.mobi": "52583924", "69v.club": "52583925", "megaresheba.ru": "52583926", "petshop.ru": "52583927", "platform.twitter.com": "52583929", "rus.bongacams20.com": "52583930", "s2.coinmarketcap.com": "52583931", "c.rusuchka.com": "52583933", "g4.sunlight.net": "52583934", "glaz.tv": "52583935", "livelib.ru": "52583936", "auth.neuralgeneration.com": "52583937", "pravda.ru": "52583938", "ru.spankbang.com": "52583940", "roblox-api.arkoselabs.com": "52584168", "itorrents-igruha.org": "52584169", "config.trackingplan.com": "52584170", "m.somon.tj": "52584171", "dorama.land": "52584172", "firebase.googleapis.com": "52584173", "hoff-cache.cdnvideo.ru": "52584174", "i.livelib.ru": "52584175", "postimgs.org": "52584176", "50.img.avito.st": "52584177", "b17.ru": "52584179", "stats.g.doubleclick.net": "52584180", "p77-sign-sg.tiktokcdn.com": "52584181", "sa.list.am": "52584182", "vseprosport.ru": "52584183", "cdn.diginetica.net": "52584184", "ros.bongacams20.com": "52584185", "play.google.com": "52584186", "google.com": "52584187", "9982906.fls.doubleclick.net": "52584188", "static-cdn77.xvideos-cdn.com": "52584189", "i.pinimg.com": "52584190", "cdn.sokolov.ru": "52584192", "mangalib.me": "52584193", "ads.pubmatic.com": "52584385", "otvetkin.info": "52584387", "free-kassa.ru": "52584388", "knigochei.org": "52584390", "cloudflareinsights.com": "52584391", "ssum-sec.casalemedia.com": "52584392", "6o6jxr40k0.kameleoon.eu": "52584393", "browser-update.org": "52584394", "play-lh.googleusercontent.com": "52584395", "cbr-xml-daily.ru": "52584396", "sync.im-apps.net": "52584397", "u.livelib.ru": "52584398", "privacyportal-eu.onetrust.com": "52584400", "static.betboom.ru": "52584401", "i.creativecommons.org": "52584402", "1000.menu": "52584405", "librato-collector.genius.com": "52584406", "cdn-st4.rtr-vesti.ru": "52584407", "virtus-img.cdnvideo.ru": "52584408", "cdn.betcity.ru": "52584409", "pool.admedo.com": "52584410", "10190325.fls.doubleclick.net": "52584412", "tevas.tv": "52584414", "uquiz.com": "52584415", "genius.com": "52584625", "dev.fandom.com": "52584626", "ecco.ru": "52584627", "criteo-sync.teads.tv": "52584629", "pomogalka.me": "52584630", "encrypted-tbn1.gstatic.com": "52584631", "static.uchi.ru": "52584633", "consumer.huawei.com": "52584634", "vmweb-va.byteoversea.com": "52584635", "lordserial.fun": "52584636", "community.cloudflare.steamstatic.com": "52584637", "h5.zuimeitianqi.com": "52584638", "sync-tm.everesttech.net": "52584639", "normans.mobi": "52584640", "doramalive.ru": "52584641", "whatsapp.com": "52584642", "encrypted-tbn2.gstatic.com": "52584645", "ase.clmbtech.com": "52584646", "lichess1.org": "52584647", "freebitco.in": "52584648", "imgs.euroki.org": "52584649", "static-login.sendpulse.com": "52584650", "static-pub.highwebmedia.com": "52584651", "static.vseigru.net": "52584652", "m.fanfiction.net": "52585057", "cdnjs.uchi.ru": "52585058", "github.githubassets.com": "52585061", "sync6.im-apps.net": "52585062", "math-ege.sdamgia.ru": "52585063", "microsoft.com": "52585064", "tr.blismedia.com": "52585065", "sbcharts.investing.com": "52585066", "js.hcaptcha.com": "52585067", "use.fontawesome.com": "52585068", "pixel-us-east.rubiconproject.com": "52585069", "media.adrcdn.com": "52585071", "abs.twimg.com": "52585073", "opengazet.com": "52585074", "pixel-eu.rubiconproject.com": "52585075", "xospital.mobi": "52585076", "pghub.io": "52585077", "tangycover.com": "52585078", "aviasales.ru": "52585080", "litlife.club": "52585081", "production-cmp.isgprivacy.cbsi.com": "52585082", "d.soccerstand.com": "52585084", "img-prod-cms-rt-microsoft-com.akamaized.net": "52585085", "storage.kameleoon.com": "52585086", "ml314.com": "52585366", "script.wikia.nocookie.net": "52585367", "hemero.ru": "52585368", "i.bcicdn.com": "52585369", "ru8.trahkino.club": "52585370", "cstatic.weborama.com": "52585371", "p16-sign.tiktokcdn-us.com": "52585373", "o4504211537854464.ingest.sentry.io": "52585375", "ru.namemc.com": "52585376", "st.rusvideos.cc": "52585377", "cdnjs.cloudflare.com": "52585379", "cdn.indexww.com": "52585380", "dcdn.heroeswm.ru": "52585381", "token.rubiconproject.com": "52585382", "znanija.com": "52585383", "static.rusvideos.vip": "52585384", "cdn-st3.rtr-vesti.ru": "52585385", "image.lichess1.org": "52585386", "bdsmpeople.co": "52585387", "xvideos5.com": "52585578", "licensebuttons.net": "52585579", "cs5.livemaster.ru": "52585581", "yt3.ggpht.com": "52585582", "styles.redditmedia.com": "52585583", "essensworld.ru": "52585584", "static.ecco.ru": "52585585", "g7.sunlight.net": "52585586", "a.wp-e.net": "52585587", "popcornnews.ru": "52585588", "nexusmods.com": "52585590", "img-cf.xvideos-cdn.com": "52585591", "fortunatenews.com": "52585592", "id.rlcdn.com": "52585593", "images-na.ssl-images-amazon.com": "52585594", "m.tiktok.com": "52585595", "m.beboo.ru": "52585596", "cdn.id5-sync.com": "52585597", "status.neuralgeneration.com": "52585598", "adwile.com": "52585599", "d.pikabu.ru": "52585600", "lastfm.freetls.fastly.net": "52585601", "ozon.ru": "52585602", "steamcdn-a.akamaihd.net": "52585603", "apis.rbxcdn.com": "52585767", "ru11.trahkino.club": "52585768", "gamesisart.ru": "52585769", "gorodovoy.ru": "52585770", "unu.im": "52585771", "t.furaffinity.net": "52585772", "prebid.media.net": "52585773", "aps.letu.ru": "52585774", "foxford.ru": "52585775", "storage.googleapis.com": "52585777", "s20.tiktokcdn.com": "52585778", "o278969.ingest.sentry.io": "52585779", "dsum.casalemedia.com": "52585780", "static.wikia.nocookie.net": "52585781", "nhentai.net": "52585782", "10903557.fls.doubleclick.net": "52585783", "pwebstat.com": "52585784", "ebay.com": "52585785", "fonts.googleapis.com": "52585786", "cybersport.push4site.com": "52585787", "api.saasexch.com": "52585788", "evt.uchi.ru": "52585789", "vseigru.net": "52585791", "thesoul-publishing-com.videoplayerhub.com": "52585792", "sfstatic.net": "52585970", "mv.outbrain.com": "52585971", "m.youtube.com": "52585972", "rt.ad-score.com": "52585973", "rusvesna.su": "52585974", "bsd.frontend.weborama.fr": "52585975", "g9.sunlight.net": "52585976", "w3-reporting.reddit.com": "52585977", "api.db-ip.com": "52585978", "help.uchi.ru": "52585980", "netdna.bootstrapcdn.com": "52585981", "prebid-server.rubiconproject.com": "52585982", "ru.investing.com": "52585983", "gdeposylka.ru": "52585984", "static.mobile-bb.com": "52585985", "beta.character.ai": "52585986", "ru.savefrom.net": "52585987", "marketingplatform.google.com": "52585988", "readmanga.live": "52585989", "videotoday.site": "52585990", "static.addtoany.com": "52585991", "case-battle.org": "52585992", "i.bimbolive.com": "52585994", "site-static-blue.betboom.ru": "52585995", "cs7.livemaster.ru": "52586110", "pay.google.com": "52586214", "mdeploy.andata.ru": "52586215", "petadopt.ru": "52586216", "knigolub.net": "52586217", "sravni.ru": "52586218", "recaptcha.net": "52586221", "g2.sunlight.net": "52586223", "cdn3.tu-tu.ru": "52586224", "imasdk.googleapis.com": "52586225", "g6.sunlight.net": "52586226", "ru.mult-porno.vip": "52586227", "2022welcome.com": "52586228", "f4club.ru": "52586229", "d7d3cf2e81d293050033-3dfc0615b0fd7b49143049256703bfce.ssl.cf1.rackcdn.com": "52586231", "static.galamart.ru": "52586233", "cdn.freekassa.ru": "52586234", "cdn.lenmit.com": "52586235", "math-oge.sdamgia.ru": "52586236", "adservice.google.me": "52586237", "a.utraff.com": "52586238", "b.cdnst.net": "52586240", "dcdn3.heroeswm.ru": "52586241", "assets.squarespace.com": "52586242", "contextual.media.net": "52586557", "static-assets.highwebmedia.com": "52586558", "xaxaxa.antibot.cloud": "52586559", "betboom.ru": "52586560", "leonardo.osnova.io": "52586561", "m.facebook.com": "52586562", "data.24smi.info": "52586564", "static1.squarespace.com": "52586565", "p1.ntvk1.ru": "52586566", "cdn.cookielaw.org": "52586568", "rus-ege.sdamgia.ru": "52586569", "love.bluesystem.me": "52586570", "pxaction.com": "52586572", "login.aliexpress.com": "52586574", "images.samsung.com": "52586575", "idrlabs.com": "52586576", "um.simpli.fi": "52586577", "st.hybrid.ai": "52586579", "faq.whatsapp.com": "52586580", "apkcombo.com": "52586582", "jnn-pa.googleapis.com": "52586584", "rf.xgroovy.com": "52586585", "gateway.reddit.com": "52586586", "st.rusvideos.porn": "52586587", "app.chaport.com": "52586888", "ru.sex-studentki.love": "52586889", "support.office.com": "52586890", "btloader.com": "52586891", "static.terratraf.io": "52586892", "bonga-cams.com": "52586893", "contents.rusvideos.org": "52586894", "script.marquiz.ru": "52586895", "multiurok.ru": "52586896", "redditstatic.com": "52586897", "cdn-st2.rtr-vesti.ru": "52586898", "shoppinglive.ru": "52586899", "static.xx.fbcdn.net": "52586901", "happywear.push4site.com": "52586902", "secure.cdn.fastclick.net": "52586903", "cdn-st1.rtr-vesti.ru": "52586904", "8649452.fls.doubleclick.net": "52586905", "desu.me": "52586906", "cs1.livemaster.ru": "52586907", "statics-marketingsites-neu-ms-com.akamaized.net": "52586908", "9942001.fls.doubleclick.net": "52586909", "post-endpoint-zypaalk44a-an.a.run.app": "52586961", "platform.instagram.com": "52586962", "sync-jp.im-apps.net": "52586963", "cas.avalon.perfdrive.com": "52586964", "websdk.appsflyer.com": "52586965", "u.openx.net": "52586966", "polyfill.io": "52586967", "code.createjs.com": "52586968", "assets2.static1-sima-land.com": "52586969", "collector.github.com": "52586970", "i.cdnreact.xyz": "52586972", "soccerstand.com": "52586973", "upa.list.am": "52586974", "catwar.su": "52586975", "redditmedia.com": "52586976", "get.geojs.io": "52586977", "cdn.rusvideos.me": "52586978", "vak345.com": "52586979", "match.org.ru": "52586980", "rus.fapcams.club": "52586981", "briefly.ru": "52586982", "i.vimeocdn.com": "52586983", "g0.sunlight.net": "52586984", "a17126690382.cdn.optimizely.com": "52586986", "yaplakal.com": "52587151", "assets.alicdn.com": "52587152", "faceit.com": "52587153", "ssm.codes": "52587154", "w9673.yclients.com": "52587155", "media.nalog.ru": "52587156", "m.addthis.com": "52587157", "cdn.ampproject.org": "52587158", "static1.eadaily.com": "52587159", "trc.taboola.com": "52587163", "f.vimeocdn.com": "52587164", "strong-jetty-308408.df.r.appspot.com": "52587165", "challenges.cloudflare.com": "52587166", "gcm.ctnsnet.com": "52587167", "pubads.g.doubleclick.net": "52587169", "elo-io.videoplayerhub.com": "52587170", "m.pornozavod.org": "52587171", "s.funpay.com": "52587172", "riki.dotabuff.com": "52587173", "siteintercept.qualtrics.com": "52587174", "sites-reviews.com": "52587175", "support.content.office.net": "52587176", "m.checkporno.cc": "52587177", "go.detmir.st": "52587179", "gigporno.red": "52587432", "aviso.bz": "52587433", "roomimg.stream.highwebmedia.com": "52587434", "11543945.fls.doubleclick.net": "52587435", "wl-adme.cf.tsp.li": "52587437", "apis.google.com": "52587438", "gdeslon.ru": "52587440", "static.indoleads.com": "52587441", "logincdn.msftauth.net": "52587444", "privacyportal-bn.my.onetrust.com": "52587445", "api.pinterest.com": "52587446", "topcor.ru": "52587447", "hcaptcha.com": "52587448", "discord.com": "52587450", "ka-f.fontawesome.com": "52587451", "b6617901a2e4abb87e1802f5ffcf3bbc.safeframe.googlesyndication.com": "52587452", "ru.pinterest.com": "52587453", "cian.ru": "52587454", "stats.klops.ru": "52587455", "rtb-csync.smartadserver.com": "52587457", "itemimg.com": "52587541", "img-cf.xnxx-cdn.com": "52587542", "instagram.astv.ru": "52587543", "ad.doubleclick.net": "52587545", "geolocation.onetrust.com": "52587760", "8655251.fls.doubleclick.net": "52587761", "g1.sunlight.net": "52587762", "cdn.confiant-integrations.net": "52587763", "6kcmxu3d7l.a.trbcdn.net": "52587764", "cdn.sendpulse.com": "52587765", "rv.furaffinity.net": "52587766", "pixel.rubiconproject.com": "52587767", "uchi.ru": "52587769", "mangapoisk.com": "52587770", "mcpehub.org": "52587771", "partner.googleadservices.com": "52587772", "s74794.cdn.ngenix.net": "52587773", "chaturbate.com": "52587774", "s7.addthis.com": "52587775", "p4-fxed5vbubflys-sgusyh6hywz2bgky-if-v6exp3-v4.metric.gstatic.com": "52587776", "rum-static.pingdom.net": "52587778", "rt.bonga-cams.com": "52587779", "webofcomics.ru": "52587780", "rtb.openx.net": "52587781", "pages.ebay.com": "52587782", "ru.xgroovy.com": "52587784", "d.pub.network": "52587785", "analytics.google.com": "52587835", "trace.mediago.io": "52587836", "img7.eadaily.com": "52587838", "ads.stickyadstv.com": "52587839", "cdn-gl.imrworldwide.com": "52587840", "futureocto.com": "52587841", "vezonchik.site": "52587842", "jut.su": "52587843", "kit.fontawesome.com": "52587844", "androeed.ru": "52587845", "ad4m.at": "52587846", "rwlib.net": "52587847", "samsung.com": "52587848", "a.ad.gt": "52587849", "strangeclocks.com": "52587850", "utro-novosti.ru": "52587852", "mobile.de": "52587853", "analytics.tiktok.com": "52587854", "code.giraff.io": "52587855", "kinoafisha.info": "52587856", "goldapple.ru": "52587857", "mcs-va.tiktokv.com": "52587858", "rr1---sn-cpux-8ovs.googlevideo.com": "52587859", "tags.tiqcdn.com": "52587860", "pushpad.xyz": "52588116", "cdn.idrlabs.com": "52588117", "g8.sunlight.net": "52588118", "cdn.adrun.ru": "52588119", "csi.gstatic.com": "52588120", "inf-oge.sdamgia.ru": "52588121", "fapcams.club": "52588122", "tracks.yclients.com": "52588123", "s.list.am": "52588124", "tube.buzzoola.com": "52588125", "s.tribalfusion.com": "52588126", "encrypted-tbn0.gstatic.com": "52588128", "static.gismeteo.st": "52588129", "rules.quantcount.com": "52588130", "mail.google.com": "52588131", "cdn.advertronic.io": "52588132", "s0.2mdn.net": "52588133", "gallery.retailrocket.net": "52588134", "scontent.xx.fbcdn.net": "52588135", "img5.eadaily.com": "52588136", "11584727.fls.doubleclick.net": "52588137", "data.nexusmods.com": "52588138", "redirect.prod.experiment.routing.cloudfront.aws.a2z.com": "52588139", "amplify.outbrain.com": "52588140", "geo.captcha-delivery.com": "52588352", "leonardo.ru": "52588353", "tlgrm.ru": "52588354", "foiz.pro": "52588355", "lf16-tiktok-common.ttwstatic.com": "52588356", "nalog.gov.ru": "52588358", "platform-cdn.sharethis.com": "52588359", "sirv.freebitco.in": "52588360", "vmmo.vten.ru": "52588361", "connect.facebook.net": "52588362", "store.steampowered.com": "52588363", "mangapoisk.ru": "52588364", "assets.adobedtm.com": "52588365", "coinpayu.com": "52588366", "67563247ca5fe1db208fbf99c35a71e8.safeframe.googlesyndication.com": "52588367", "pornozavod.cc": "52588368", "px.owneriq.net": "52588369", "rtb-eu-warsaw.intent.ai": "52588371", "js-sec.indexww.com": "52588373", "aternos.org": "52588374", "content.pornobolt.cc": "52588375", "author.today": "52588376", "cdn.intergi.com": "52588377", "m.rusuchka.com": "52588378", "tag.durationmedia.net": "52588648", "rs.fullstory.com": "52588649", "api-gravity.coinmarketcap.com": "52588650", "mon-va.byteoversea.com": "52588651", "cdn2.static1-sima-land.com": "52588653", "o4504678871072768.ingest.sentry.io": "52588654", "static.eldorado.ru": "52588655", "905efd75dd80b8d368a520d8807ff8a0.safeframe.googlesyndication.com": "52588656", "e.catwar.su": "52588657", "ataka-titanov.com": "52588658", "reddit.com": "52588659", "static.captcha-delivery.com": "52588660", "g3.sunlight.net": "52588661", "mangamammy.ru": "52588663", "s.pinimg.com": "52588664", "aeis.alicdn.com": "52588665", "a1697d8d474ebce80580b53181c064c5.safeframe.googlesyndication.com": "52588666"}