{"Incapsula": {"https://www.network.com.tr/Areas/sf/dist/fonts/TTNormsPro-Regular.woff2": {"size": "68616", "type": "application/font-woff2"}, "https://www.rudaw.net/images/default/web/default-listing.jpg": {"size": "212", "type": "text/html"}, "https://www.decathlon.com.tr/client/app/3656.2f74174cbf44c3cf4cd5.js": {"size": "10831", "type": "application/javascript; charset=UTF-8"}, "https://www.decathlon.com.tr/render/Roboto-Bold-tr.4ea59e28e4dc93da2596.woff2": {"size": "8064", "type": "font/woff2"}, "https://www.decathlon.com.tr/client/app/1130.ba1bc5cd48af546ec3b1.js": {"size": "432", "type": "application/javascript; charset=UTF-8"}, "https://www.rudaw.net/images/logo.svg": {"size": "212", "type": "text/html"}, "https://www.network.com.tr/Areas/sf/dist/javascripts/home.js?v=1.0.0.81": {"size": "40749", "type": "application/x-javascript"}, "https://www.rudaw.net/styles/fonts/sr/NewRudaw-Regular.woff2": {"size": "212", "type": "text/html"}, "https://www.network.com.tr/Areas/sf/dist/stylesheets/main.css?v=1.0.0.81": {"size": "36449", "type": "text/css"}, "https://www.decathlon.com.tr/client/app/6184.bb5ae24dbfe975c31d63.js": {"size": "7722", "type": "application/javascript; charset=UTF-8"}, "https://www.decathlon.com.tr/client/app/1594.7ace74bfea04ef61f217.js": {"size": "11613", "type": "application/javascript; charset=UTF-8"}, "https://www.network.com.tr/Areas/sf/dist/javascripts/main.js?v=1.0.0.81": {"size": "101680", "type": "application/x-javascript"}, "https://www.network.com.tr/Areas/sf/dist/fonts/FreightMicroPro-Book.woff2": {"size": "29972", "type": "application/font-woff2"}, "https://www.rudaw.net/images/arabic-logo.png": {"size": "212", "type": "text/html"}, "https://www.rudaw.net/s3/rudaw.net/ContentFiles/724414Image1.jpg?mode=crop&quality=70&rand=1&scale=both&w=558&h=348&version=5141032": {"size": "212", "type": "text/html"}, "https://www.rudaw.net/images/ico-logo.svg": {"size": "212", "type": "text/html"}, "https://www.rudaw.net/s3/rudaw.net/ContentFiles/724392Highlighted%20Image.jpg?mode=crop&quality=70&rand=1&scale=both&w=2000&h=750&version=5140662&isMobileBrowser=False": {"size": "212", "type": "text/html"}, "https://www.decathlon.com.tr/client/app/1575.c23cd9ec14dad8179d91.js": {"size": "5871", "type": "application/javascript; charset=UTF-8"}, "https://www.network.com.tr/assets/V2/img/payment-maximum.png": {"size": "3181", "type": "image/png"}, "https://www.network.com.tr/assets/v2/img/Network.svg": {"size": "1863", "type": "image/svg+xml"}, "https://www.beymen.com/customer/getheaderinfo": {"size": "748", "type": "text/html"}, "https://www.rudaw.net/bundles/jshomepage?v=7i7p-JXxqoAOUeEuOa3pDpyKR6TUucwlDPIAt0VTCpc1": {"size": "212", "type": "text/html"}, "https://www.decathlon.com.tr/tr/ajax/nfs/translations": {"size": "879", "type": "text/html"}, "https://stream-762.optimove.net/": {"size": "140", "type": "text/html; charset=utf-8"}, "https://www.network.com.tr/Areas/sf/dist/fonts/TTNormsPro-Bold.woff2": {"size": "67492", "type": "application/font-woff2"}, "https://www.beymen.com/assets-sf/desktop/js/vendors/vendors.bundle.js?v=5.110.1": {"size": "749", "type": "text/html"}, "https://www.rudaw.net/Library/EditorImages/Comp%2010_00000.jpg": {"size": "158", "type": "text/html; charset=UTF-8"}, "https://www.rudaw.net/images/ico-program-clock.svg": {"size": "212", "type": "text/html"}, "https://www.decathlon.com.tr/client/app/5366.cde83e3b841c83219c08.js": {"size": "3649", "type": "application/javascript; charset=UTF-8"}, "https://www.decathlon.com.tr/tr/ajax/nfs/menu": {"size": "882", "type": "text/html"}, "https://www.rudaw.net/_Incapsula_Resource?SWHANEDL=1027734139021543259,3654277839067451693,10713740946436120521,1033210": {"size": "14", "type": "text/plain"}, "https://www.decathlon.com.tr/client/app/5451.13f7274ef6de48d814bb.js": {"size": "26823", "type": "application/javascript; charset=UTF-8"}, "https://www.network.com.tr/assets/V2/img/payment-bonus.png": {"size": "3174", "type": "image/png"}, "https://www.decathlon.com.tr/render/Roboto-Regular-tr.2461a71c09eb1154216c.woff2": {"size": "8112", "type": "font/woff2"}, "https://www.network.com.tr/assets/v2/img/aymarka-logo.svg": {"size": "3655", "type": "image/svg+xml"}, "https://www.network.com.tr/assets/V2/img/payment-card-finans.png": {"size": "3001", "type": "image/png"}, "https://www.beymen.com/assets-sf/desktop/css/home.css?v=5.110.1": {"size": "750", "type": "text/html"}, "https://www.rudaw.net/images/pixel.gif": {"size": "212", "type": "text/html"}, "https://www.decathlon.com.tr/client/app/8367.6b56317e2063ff948778.js": {"size": "6361", "type": "application/javascript; charset=UTF-8"}, "https://decathlon.com.tr/ectr/static/homepage/js/main.js": {"size": "0", "type": "unknown"}, "https://www.rudaw.net/Library/EditorImages/banner-march-2022/SH%20kurdi.gif": {"size": "158", "type": "text/html; charset=UTF-8"}, "https://www.decathlon.com.tr/_Incapsula_Resource?SWKMTFSR=1&e=0.5713472869410325": {"size": "1", "type": "text/plain"}, "https://www.decathlon.com.tr/client/app/3911.ce064e1ecf706c93afbe.js": {"size": "38223", "type": "application/javascript; charset=UTF-8"}, "https://www.decathlon.com.tr/render/didomi.3725e32d514f63c56db3.js": {"size": "764", "type": "application/javascript; charset=UTF-8"}, "https://www.decathlon.com.tr/client/app/1216.66bf99118b306074090d.js": {"size": "7279", "type": "application/javascript; charset=UTF-8"}, "https://www.decathlon.com.tr/client/app/6241.a085a35f8bfe44367c2a.js": {"size": "7695", "type": "application/javascript; charset=UTF-8"}, "https://www.network.com.tr/assets/V2/img/payment-master-card.png": {"size": "2330", "type": "image/png"}, "https://www.decathlon.com.tr/_Incapsula_Resource?SWJIYLWA=719d34d31c8e3a6e6fffd425f7e032f3&ns=1&cb=1612454833": {"size": "21158", "type": "application/javascript"}, "https://www.beymen.com/assets-sf/desktop/js/pages/home.js?v=5.110.1": {"size": "749", "type": "text/html"}, "https://www.network.com.tr/assets/V2/img/payment-visa.png": {"size": "925", "type": "image/png"}, "https://www.beymen.com/assets-sf/desktop/js/pages/main.js?v=5.110.1": {"size": "751", "type": "text/html"}, "https://www.rudaw.net/Library/EditorImages/banner-march-2022/Banner.gif": {"size": "158", "type": "text/html; charset=UTF-8"}, "https://www.decathlon.com.tr/client/app/3492.a3d27e23f1b14eb815d4.js": {"size": "8599", "type": "application/javascript; charset=UTF-8"}, "https://www.decathlon.com.tr/tr/ajax/loadData/content/Web/NFS/Ajax/Header": {"size": "876", "type": "text/html"}, "https://www.decathlon.com.tr/client/app/5124.fbd87a25703a9ddeb369.js": {"size": "48756", "type": "application/javascript; charset=UTF-8"}, "https://www.rudaw.net/bundles/scriptshp?v=VBzLeF6dQXxJy61NURCWUYd-O5c9Xj4DIdJ1IIGEfIA1": {"size": "212", "type": "text/html"}, "https://www.rudaw.net/bundles/otherscriptsrtl?v=tPrOybzGsYl1MUiOTmw-ZzTdjgNEUdhwuYmr2pFBqqY1": {"size": "212", "type": "text/html"}, "https://www.decathlon.com.tr/client/app/2840.bca1180ba3c534629c2b.js": {"size": "6381", "type": "application/javascript; charset=UTF-8"}, "https://www.rudaw.net/Library/EditorImages/banner-march-2022/web.png": {"size": "158", "type": "text/html; charset=UTF-8"}, "https://www.decathlon.com.tr/client/app/8159.84c7ca7b1861f0efd747.js": {"size": "11706", "type": "application/javascript; charset=UTF-8"}, "https://www.decathlon.com.tr/client/app/client.c968e889d52b465a73aa.js": {"size": "136938", "type": "application/javascript; charset=UTF-8"}, "https://www.network.com.tr/_Incapsula_Resource?SWKMTFSR=1&e=0.8606465557521885": {"size": "14", "type": "text/plain"}, "https://www.rudaw.net/s3/rudaw.net/ContentFiles/724387Highlighted%20Image.jpg?mode=crop&quality=70&rand=1&scale=both&w=2000&h=750&version=5140456&isMobileBrowser=False": {"size": "212", "type": "text/html"}, "https://www.rudaw.net/s3/rudaw.net/ContentFiles/724420Highlighted%20Image.jpg?mode=crop&quality=70&rand=1&scale=both&w=2000&h=750&version=5140990&isMobileBrowser=False": {"size": "212", "type": "text/html"}, "https://www.decathlon.com.tr/client/app/7541.99fa606060d313c90754.js": {"size": "23820", "type": "application/javascript; charset=UTF-8"}, "https://www.beymen.com/": {"size": "750", "type": "text/html"}, "https://www.network.com.tr/Areas/sf/dist/fonts/NetWork.woff2": {"size": "7224", "type": "application/font-woff2"}, "https://www.beymen.com/cart/getcartitemcount?&ts=1680562771236": {"size": "748", "type": "text/html"}, "https://www.network.com.tr/BasketV2/getCartItemCount": {"size": "171", "type": "application/json; charset=utf-8"}, "https://www.decathlon.com.tr/client/app/3280.983fbdd2e5113555d556.js": {"size": "3856", "type": "application/javascript; charset=UTF-8"}, "https://www.rudaw.net/Library/EditorImages/banner-march-2022/banner-2023/Rudaw%20FIB%201140x100%20Kurdish.png": {"size": "158", "type": "text/html; charset=UTF-8"}, "https://www.decathlon.com.tr/render/RobotoCondensed-Bold-tr.80399eb5bf0c5ca4b8bc.woff2": {"size": "8000", "type": "font/woff2"}, "https://www.network.com.tr/assets/V2/img/payment-paraf.png": {"size": "3189", "type": "image/png"}, "https://www.rudaw.net/_Incapsula_Resource?ES2LURCT=67&t=78&d=complete%20(s%3A1%2Cc%3A131%2Cr%3A349)": {"size": "14", "type": "text/plain"}, "https://www.decathlon.com.tr/render/smartbanner.min.tr.a94be9b4e1f38ccea29b.js": {"size": "3039", "type": "application/javascript; charset=UTF-8"}, "https://www.network.com.tr/_Incapsula_Resource?SWJIYLWA=719d34d31c8e3a6e6fffd425f7e032f3&ns=1&cb=1229206767": {"size": "14", "type": "text/plain"}, "https://www.decathlon.com.tr/render/RobotoCondensed-Regular-tr.2ff0a6f45f4f1a57e988.woff2": {"size": "8064", "type": "font/woff2"}, "https://www.decathlon.com.tr/client/app/8275.5938240a7183f076a661.js": {"size": "11960", "type": "application/javascript; charset=UTF-8"}, "https://www.beymen.com/api/favorite/count?&ts=1680562771235": {"size": "749", "type": "text/html"}, "https://www.decathlon.com.tr/": {"size": "882", "type": "text/html"}, "https://www.network.com.tr/Areas/sf/dist/stylesheets/new-grid-system.css?v=1.0.0.81": {"size": "10720", "type": "text/css"}, "https://www.rudaw.net/s3/rudaw.net/ContentFiles/724424Image1.jpg?mode=crop&quality=70&rand=1&scale=both&w=558&h=348&version=5141080": {"size": "212", "type": "text/html"}, "https://www.decathlon.com.tr/client/style/style.0425fe3bb2faee22ee09.css": {"size": "3664", "type": "text/css; charset=UTF-8"}, "https://www.network.com.tr/Areas/sf/dist/fonts/TTNormsPro-DemiBold.woff2": {"size": "68836", "type": "application/font-woff2"}, "https://www.rudaw.net/_Incapsula_Resource?SWKMTFSR=1&e=0.9223170050091012": {"size": "14", "type": "text/plain"}, "https://www.rudaw.net/images/mostwatchedIcon.png": {"size": "212", "type": "text/html"}, "https://www.network.com.tr/Areas/sf/dist/stylesheets/home.css?v=1.0.0.81": {"size": "8897", "type": "text/css"}, "https://www.rudaw.net/styles/cssSrHP?v=P8cd4PEu2Eapr8JNoaAFZlwaU5MApLK11F1Q4sjogpc1": {"size": "212", "type": "text/html"}, "https://www.rudaw.net/images/ico-home-photo.svg": {"size": "212", "type": "text/html"}, "https://www.rudaw.net/images/ico-play-episode-2.svg": {"size": "212", "type": "text/html"}, "https://www.decathlon.com.tr/client/app/1381.b8adb1d52b79148f0bb1.js": {"size": "12039", "type": "application/javascript; charset=UTF-8"}, "https://www.rudaw.net/Library/EditorImages/banner-march-2022/Alin%20Kurdi.jpg": {"size": "158", "type": "text/html; charset=UTF-8"}, "https://www.rudaw.net/images/pixel.gif?mode=crop&quality=70&rand=1&scale=both&w=2000&h=750": {"size": "212", "type": "text/html"}, "https://www.rudaw.net/images/ico-android.svg": {"size": "212", "type": "text/html"}, "https://www.rudaw.net/s3/rudaw.net/ContentFiles/724395Image1.jpg?mode=crop&quality=70&rand=1&scale=both&w=558&h=348&version=5141073": {"size": "212", "type": "text/html"}, "https://www.decathlon.com.tr/client/app/8187.07de2a6c3ae1711d9919.js": {"size": "9940", "type": "application/javascript; charset=UTF-8"}, "https://www.rudaw.net/": {"size": "212", "type": "text/html"}, "https://www.rudaw.net/styles/fonts/sr/NewRudaw-Bold.woff2": {"size": "212", "type": "text/html"}, "https://www.rudaw.net/images/carousel-programs-next.png": {"size": "212", "type": "text/html"}, "https://www.rudaw.net/api/News/BreakingNewsHome?lang=Sorani": {"size": "158", "type": "text/html; charset=UTF-8"}, "https://www.decathlon.com.tr/client/app/335.ac166d382df0c9f449b7.js": {"size": "4483", "type": "application/javascript; charset=UTF-8"}, "https://www.decathlon.com.tr/client/style/vitamix.7b894c53258ce81fcc8f29bd16ca59cb.ttf": {"size": "62560", "type": "font/ttf"}, "https://www.rudaw.net/images/transparent.png": {"size": "212", "type": "text/html"}, "https://www.decathlon.com.tr/client/style/vtmn-style.a69d2f45699f94b3c96c.css": {"size": "27029", "type": "text/css; charset=UTF-8"}, "https://www.rudaw.net/images/bg-dotted-section.jpg": {"size": "212", "type": "text/html"}, "https://www.decathlon.com.tr/render/icons.c6839240d86f3e16a32a.svg": {"size": "38059", "type": "image/svg+xml"}, "https://www.decathlon.com.tr/client/app/5117.4c7e04b6296a3950338d.js": {"size": "5977", "type": "application/javascript; charset=UTF-8"}, "https://www.rudaw.net/bundles/jquery?v=fmXCw8kSt9AeIEHAp-2nCW_-lPtxCBRAHPceQDO01w41": {"size": "212", "type": "text/html"}, "https://www.network.com.tr/Areas/sf/dist/fonts/AvenirLTPro-Medium.woff2": {"size": "16172", "type": "application/font-woff2"}, "https://www.decathlon.com.tr/client/app/2857.7db3f4597803c3f8dd12.js": {"size": "6636", "type": "application/javascript; charset=UTF-8"}, "https://www.network.com.tr/assets/V2/img/payment-axess.png": {"size": "2630", "type": "image/png"}, "https://www.decathlon.com.tr/client/app/7024.62db40f242d3769ba13c.js": {"size": "2029", "type": "application/javascript; charset=UTF-8"}, "https://www.rudaw.net/images/ico-header-search.svg": {"size": "212", "type": "text/html"}, "https://www.rudaw.net/_Incapsula_Resource?SWJIYLWA=719d34d31c8e3a6e6fffd425f7e032f3&ns=4&cb=694807975": {"size": "14", "type": "text/plain"}, "https://www.rudaw.net/images/ico-apple.svg": {"size": "212", "type": "text/html"}, "https://www.rudaw.net/images/menu-toggle.svg": {"size": "212", "type": "text/html"}, "https://realtime-762.optimove.net/reportEvent": {"size": "12", "type": "text/plain; charset=utf-8"}, "https://www.network.com.tr/Areas/sf/dist/fonts/TTNormsPro-Normal.woff2": {"size": "68744", "type": "application/font-woff2"}, "https://www.decathlon.com.tr/render/smartbanner.tr.19255d232a1e6847b4b8.css": {"size": "700", "type": "text/css; charset=UTF-8"}, "https://www.decathlon.com.tr/client/style/vtmn-tailwind.d213ec2af518455020ad.css": {"size": "20802", "type": "text/css; charset=UTF-8"}, "https://www.network.com.tr/": {"size": "80211", "type": "text/html; charset=utf-8"}, "https://www.rudaw.net/images/ico-video.svg": {"size": "212", "type": "text/html"}, "https://www.rudaw.net/_Incapsula_Resource?SWJIYLWA=5074a744e2e3d891814e9a2dace20bd4,719d34d31c8e3a6e6fffd425f7e032f3": {"size": "14", "type": "text/plain"}, "https://www.decathlon.com.tr/client/app/7369.2a14b9c66f15a84d31ec.js": {"size": "11642", "type": "application/javascript; charset=UTF-8"}, "https://www.rudaw.net/Library/EditorImages/Rice-Oil.jpg": {"size": "158", "type": "text/html; charset=UTF-8"}, "https://www.decathlon.com.tr/client/app/6959.36e73fe67308f6276dfc.js": {"size": "48864", "type": "application/javascript; charset=UTF-8"}, "https://www.rudaw.net/images/carousel-programs-prev.png": {"size": "212", "type": "text/html"}, "https://www.rudaw.net/_Incapsula_Resource?SWKMTFSR=1&e=0.9058028704226284": {"size": "14", "type": "text/plain"}, "https://www.decathlon.com.tr/client/app/2126.90fb1b4d85e9a401ba2a.js": {"size": "3724", "type": "application/javascript; charset=UTF-8"}, "https://www.decathlon.com.tr/client/app/1164.58bc4efddf7acea8d627.js": {"size": "8964", "type": "application/javascript; charset=UTF-8"}, "https://www.beymen.com/assets-sf/desktop/css/main.css?v=5.110.1": {"size": "749", "type": "text/html"}, "https://www.network.com.tr/assets/V2/img/payment-yk-world.png": {"size": "3245", "type": "image/png"}, "https://www.decathlon.com.tr/client/app/2332.4fb347e5608ab539d533.js": {"size": "9070", "type": "application/javascript; charset=UTF-8"}, "https://www.network.com.tr/Areas/sf/dist/fonts/TTNormsPro-Medium.woff2": {"size": "67548", "type": "application/font-woff2"}, "https://www.decathlon.com.tr/client/app/9776.911ecc46ae606c3069e5.js": {"size": "3100", "type": "application/javascript; charset=UTF-8"}, "https://www.decathlon.com.tr/client/app/5692.2048e7a13423e33f1d6e.js": {"size": "2210", "type": "application/javascript; charset=UTF-8"}, "https://www.decathlon.com.tr/client/app/4638.60064f098c7377844f76.js": {"size": "23486", "type": "application/javascript; charset=UTF-8"}, "https://www.rudaw.net/bundles/SkwidScripts?v=Brp1JzK3M3DuNPgyGcu9ZP1-jeVVzCk9j_K_IhVH6pU1": {"size": "212", "type": "text/html"}, "https://www.rudaw.net/images/bg-video.jpg": {"size": "212", "type": "text/html"}, "https://www.network.com.tr/Areas/sf/dist/img/pageloader.gif": {"size": "9214", "type": "image/gif"}, "https://www.decathlon.com.tr/client/app/9610.cecb7b3a1bb1a270c847.js": {"size": "2531", "type": "application/javascript; charset=UTF-8"}, "https://www.decathlon.com.tr/client/app/6987.35118df64c56532c9565.js": {"size": "38678", "type": "application/javascript; charset=UTF-8"}}}